example/cat_from_astropy.py
tilemaker/__init__.py
tilemaker/settings.py
tilemaker/analysis/__init__.py
tilemaker/analysis/aperture.py
tilemaker/analysis/core.py
tilemaker/analysis/histogram.py
tilemaker/analysis/products.py
tilemaker/analysis/providers.py
tilemaker/client/__init__.py
tilemaker/client/cli.py
tilemaker/client/simple.py
tilemaker/metadata/__init__.py
tilemaker/metadata/boxes.py
tilemaker/metadata/core.py
tilemaker/metadata/database.py
tilemaker/metadata/definitions.py
tilemaker/metadata/fits.py
tilemaker/metadata/generation.py
tilemaker/metadata/orm.py
tilemaker/metadata/sources.py
tilemaker/processing/__init__.py
tilemaker/processing/extractor.py
tilemaker/processing/renderer.py
tilemaker/providers/__init__.py
tilemaker/providers/caching.py
tilemaker/providers/core.py
tilemaker/providers/fits.py
tilemaker/server/__init__.py
tilemaker/server/analysis.py
tilemaker/server/app.py
tilemaker/server/auth.py
tilemaker/server/caching.py
tilemaker/server/highlights.py
tilemaker/server/histogram.py
tilemaker/server/maps.py
tilemaker/server/sources.py
tilemaker/server/static/index.html
tilemaker/server/static/so-tileviewer.png
tilemaker/server/static/assets/index-CjsAYQpv.css
tilemaker/server/static/assets/index-DzlCungg.js
tilemaker-2.3.3.dist-info/METADATA
tilemaker-2.3.3.dist-info/WHEEL
tilemaker-2.3.3.dist-info/entry_points.txt
tilemaker-2.3.3.dist-info/top_level.txt
tilemaker-2.3.3.dist-info/RECORD
