Metadata-Version: 2.4
Name: tilemaker
Version: 2.3.3
Requires-Python: >=3.11
Requires-Dist: pixell
Requires-Dist: pydantic-settings
Requires-Dist: numpy
Requires-Dist: numpydantic
Requires-Dist: fastapi
Requires-Dist: uvicorn
Requires-Dist: matplotlib
Requires-Dist: astropy
Requires-Dist: fastapi-cache2
Requires-Dist: typer
Requires-Dist: soauth
Requires-Dist: cachetools
Requires-Dist: pymemcache
Requires-Dist: structlog
Requires-Dist: astropydantic
